adan_pytorch/__init__.py
adan_pytorch/adan.py
adan_pytorch-0.1.0.dist-info/LICENSE
adan_pytorch-0.1.0.dist-info/METADATA
adan_pytorch-0.1.0.dist-info/WHEEL
adan_pytorch-0.1.0.dist-info/top_level.txt
adan_pytorch-0.1.0.dist-info/RECORD
