Metadata-Version: 2.1
Name: adan-pytorch
Version: 0.1.0
Summary: Adan - (ADAptive Nesterov momentum algorithm) Optimizer in Pytorch
Home-page: https://github.com/lucidrains/Adan-pytorch
Author: Phil Wang
Author-email: lucidrains@gmail.com
License: MIT
Keywords: artificial intelligence,deep learning,optimizer
Classifier: Development Status :: 4 - Beta
Classifier: Intended Audience :: Developers
Classifier: Topic :: Scientific/Engineering :: Artificial Intelligence
Classifier: License :: OSI Approved :: MIT License
Classifier: Programming Language :: Python :: 3.6
License-File: LICENSE
Requires-Dist: torch (>=1.6)
